findlist/__init__.py
findlist/finder.py
findListInList-0.0.3.dist-info/METADATA
findListInList-0.0.3.dist-info/WHEEL
findListInList-0.0.3.dist-info/top_level.txt
findListInList-0.0.3.dist-info/RECORD
