Metadata-Version: 2.1
Name: findListInList
Version: 0.0.3
Summary: A libray that tells you the poition of a list in another list.
Author-email: BlackWhiteDuke <nemoliu2010@gmail.com>
Classifier: Programming Language :: Python :: 3
Classifier: License :: OSI Approved :: MIT License
Classifier: Operating System :: OS Independent
Requires-Python: >=3.7
